fakepy/django_storage/__init__.py
fakepy/django_storage/aws_s3.py
fakepy/django_storage/azure_cloud_storage.py
fakepy/django_storage/base.py
fakepy/django_storage/cloud.py
fakepy/django_storage/filesystem.py
fakepy/django_storage/google_cloud_storage.py
fakepy/django_storage/tests/__init__.py
fakepy/django_storage/tests/data.py
fakepy/django_storage/tests/test_aws_s3_storage.py
fakepy/django_storage/tests/test_azure_cloud_storage.py
fakepy/django_storage/tests/test_filesystem_storage.py
fakepy/django_storage/tests/test_google_cloud_storage.py
fake_py_django_storage-0.1.2.dist-info/LICENSE
fake_py_django_storage-0.1.2.dist-info/METADATA
fake_py_django_storage-0.1.2.dist-info/WHEEL
fake_py_django_storage-0.1.2.dist-info/top_level.txt
fake_py_django_storage-0.1.2.dist-info/RECORD
