Metadata-Version: 2.2
Name: fake-py-django-storage
Version: 0.1.2
Summary: Django storage for fake.py
Author-email: Artur Barseghyan <artur.barseghyan@gmail.com>
Maintainer-email: Artur Barseghyan <artur.barseghyan@gmail.com>
License: MIT
Project-URL: Homepage, https://github.com/barseghyanartur/fake-py-django-storage/
Project-URL: Issues, https://github.com/barseghyanartur/fake-py-django-storage/issues
Project-URL: Documentation, https://fake-py-django-storage.readthedocs.io/
Project-URL: Repository, https://github.com/barseghyanartur/fake-py-django-storage/
Project-URL: Changelog, https://fake-py-django-storage.readthedocs.io/en/latest/changelog.html
Keywords: fake data,test data
Classifier: Development Status :: 4 - Beta
Classifier: Intended Audience :: Developers
Classifier: License :: OSI Approved :: MIT License
Classifier: Operating System :: OS Independent
Classifier: Programming Language :: Python :: 3
Classifier: Programming Language :: Python :: 3.10
Classifier: Programming Language :: Python :: 3.11
Classifier: Programming Language :: Python :: 3.12
Classifier: Programming Language :: Python :: 3.9
Classifier: Programming Language :: Python
Classifier: Topic :: Software Development :: Testing
Classifier: Topic :: Software Development
License-File: LICENSE
Requires-Dist: fake.py>=0.9.5
Requires-Dist: django
Provides-Extra: all
Requires-Dist: fake-py-django-storage[azure,dev,docs,gcs,s3,test]; extra == "all"
Provides-Extra: dev
Requires-Dist: black; extra == "dev"
Requires-Dist: detect-secrets; extra == "dev"
Requires-Dist: doc8; extra == "dev"
Requires-Dist: ipython; extra == "dev"
Requires-Dist: isort; extra == "dev"
Requires-Dist: mypy; extra == "dev"
Requires-Dist: pip-tools; extra == "dev"
Requires-Dist: pydoclint; extra == "dev"
Requires-Dist: ruff; extra == "dev"
Requires-Dist: twine; extra == "dev"
Requires-Dist: uv; extra == "dev"
Provides-Extra: test
Requires-Dist: django; extra == "test"
Requires-Dist: parametrize; extra == "test"
Requires-Dist: pytest; extra == "test"
Requires-Dist: pytest-cov; extra == "test"
Requires-Dist: pytest-django; extra == "test"
Requires-Dist: pytest-rst; extra == "test"
Requires-Dist: moto; extra == "test"
Provides-Extra: docs
Requires-Dist: sphinx<6.0; extra == "docs"
Requires-Dist: sphinx-rtd-theme>=1.3.0; extra == "docs"
Requires-Dist: sphinx-no-pragma; extra == "docs"
Provides-Extra: gcs
Requires-Dist: django-storages[google]; extra == "gcs"
Provides-Extra: s3
Requires-Dist: django-storages[s3]; extra == "s3"
Provides-Extra: azure
Requires-Dist: django-storages[azure]; extra == "azure"
